MANIFEST.in
README.rst
setup.py
aliyun_python_sdk_tag_inner.egg-info/PKG-INFO
aliyun_python_sdk_tag_inner.egg-info/SOURCES.txt
aliyun_python_sdk_tag_inner.egg-info/dependency_links.txt
aliyun_python_sdk_tag_inner.egg-info/requires.txt
aliyun_python_sdk_tag_inner.egg-info/top_level.txt
aliyunsdktag_inner/__init__.py
aliyunsdktag_inner/request/__init__.py
aliyunsdktag_inner/request/v20181109/InnerFixRegionRequest.py
aliyunsdktag_inner/request/v20181109/InnerListTagResourcesRequest.py
aliyunsdktag_inner/request/v20181109/InnerTagResourcesRequest.py
aliyunsdktag_inner/request/v20181109/InnerUntagResourcesRequest.py
aliyunsdktag_inner/request/v20181109/QueryServiceCodeRequest.py
aliyunsdktag_inner/request/v20181109/TagResourcesSystemTagsRequest.py
aliyunsdktag_inner/request/v20181109/__init__.py